slips/__init__.py
slips/config.py
slips/core.py
slips/dataset_manager.py
slips/exceptions.py
slips/log_watcher.py
slips/slips_alert_monitor.py
slips/slips_manager.py
slips/slips_multiInstance_manager.py
slips/slips_setup.py
slips/utils.py
slips/zeek_script_manager.py
slips/StratosphereLinuxIPS/.dockerignore
slips/StratosphereLinuxIPS/.gitmodules
slips/StratosphereLinuxIPS/.pre-commit-config.yaml
slips/StratosphereLinuxIPS/.readthedocs.yaml
slips/StratosphereLinuxIPS/.secrets.baseline
slips/StratosphereLinuxIPS/CHANGELOG.md
slips/StratosphereLinuxIPS/CITATION.cff
slips/StratosphereLinuxIPS/Makefile
slips/StratosphereLinuxIPS/README.md
slips/StratosphereLinuxIPS/VERSION
slips/StratosphereLinuxIPS/__init__.py
slips/StratosphereLinuxIPS/conftest.py
slips/StratosphereLinuxIPS/kalipso.sh
slips/StratosphereLinuxIPS/package.json
slips/StratosphereLinuxIPS/pytest.ini
slips/StratosphereLinuxIPS/slips.py
slips/StratosphereLinuxIPS/webinterface.sh
slips/StratosphereLinuxIPS/.github/dependabot.yml
slips/StratosphereLinuxIPS/.github/pull_request_template.md
slips/StratosphereLinuxIPS/.github/ISSUE_TEMPLATE/bug_report.md
slips/StratosphereLinuxIPS/.github/ISSUE_TEMPLATE/feature-request-template.md
slips/StratosphereLinuxIPS/.github/ISSUE_TEMPLATE/task.md
slips/StratosphereLinuxIPS/.github/workflows/install-slips-dependencies.yml
slips/StratosphereLinuxIPS/.github/workflows/integration-tests.yml
slips/StratosphereLinuxIPS/.github/workflows/publish-slips-images.yml
slips/StratosphereLinuxIPS/.github/workflows/unit-tests.yml
slips/StratosphereLinuxIPS/.github/workflows/update-code-docs.yml
slips/StratosphereLinuxIPS/LICENSES/GPL-2.0-only.txt
slips/StratosphereLinuxIPS/config/JA3_feeds.csv
slips/StratosphereLinuxIPS/config/RiskIQ_credentials
slips/StratosphereLinuxIPS/config/SSL_feeds.csv
slips/StratosphereLinuxIPS/config/TI_feeds.csv
slips/StratosphereLinuxIPS/config/iris_config.yaml
slips/StratosphereLinuxIPS/config/logstash.conf
slips/StratosphereLinuxIPS/config/redis.conf
slips_sdk-0.1.13.dist-info/licenses/LICENSE
slips_sdk-0.1.13.dist-info/METADATA
slips_sdk-0.1.13.dist-info/WHEEL
slips_sdk-0.1.13.dist-info/entry_points.txt
slips_sdk-0.1.13.dist-info/top_level.txt
slips_sdk-0.1.13.dist-info/RECORD
