Metadata-Version: 2.4
Name: slips-sdk
Version: 0.1.13
Summary: SDK for interacting with slips IDS components
Home-page: https://github.com/jenilv-07/slips-sdk.git
Author: Jenil Vekariya
Author-email: vekariyajenil888@gmail.com
Project-URL: Documentation, https://github.com/jenilv-07/slips-sdk#readme
Project-URL: Source, https://github.com/jenilv-07/slips-sdk
Project-URL: Issues, https://github.com/jenilv-07/slips-sdk/issues
Classifier: Programming Language :: Python :: 3
Classifier: Operating System :: POSIX :: Linux
Classifier: License :: OSI Approved :: GNU Affero General Public License v3
Requires-Python: >=3.10
License-File: LICENSE
Dynamic: author
Dynamic: author-email
Dynamic: classifier
Dynamic: description
Dynamic: description-content-type
Dynamic: home-page
Dynamic: license-file
Dynamic: project-url
Dynamic: requires-python
Dynamic: summary
